[{"month":1,"ticker":"CVX","years":19,"sector":"Energy","max_change":"0.1626","min_change":"-0.1169","marketcap":"381251553837","avg_change":"-0.0137","median_change":"-0.0198","positive_closes":8,"positive_months_perc":"0.4211"},{"month":2,"ticker":"CVX","years":19,"sector":"Energy","max_change":"0.1629","min_change":"-0.1273","marketcap":"381251553837","avg_change":"0.0079","median_change":"0.0241","positive_closes":13,"positive_months_perc":"0.6842"},{"month":3,"ticker":"CVX","years":19,"sector":"Energy","max_change":"0.1341","min_change":"-0.2293","marketcap":"381251553837","avg_change":"0.0274","median_change":"0.0269","positive_closes":15,"positive_months_perc":"0.7895"},{"month":4,"ticker":"CVX","years":19,"sector":"Energy","max_change":"0.3236","min_change":"-0.1867","marketcap":"381251553837","avg_change":"0.0293","median_change":"0.0148","positive_closes":12,"positive_months_perc":"0.6316"},{"month":5,"ticker":"CVX","years":19,"sector":"Energy","max_change":"0.1174","min_change":"-0.1019","marketcap":"381251553837","avg_change":"-0.0120","median_change":"-0.0006","positive_closes":10,"positive_months_perc":"0.5263"},{"month":6,"ticker":"CVX","years":18,"sector":"Energy","max_change":"0.0916","min_change":"-0.1808","marketcap":"381251553837","avg_change":"-0.0024","median_change":"0.0031","positive_closes":10,"positive_months_perc":"0.5556"},{"month":7,"ticker":"CVX","years":18,"sector":"Energy","max_change":"0.1172","min_change":"-0.1394","marketcap":"381251553837","avg_change":"0.0101","median_change":"0.0128","positive_closes":12,"positive_months_perc":"0.6667"},{"month":8,"ticker":"CVX","years":18,"sector":"Energy","max_change":"0.0528","min_change":"-0.0721","marketcap":"381251553837","avg_change":"-0.0189","median_change":"-0.0175","positive_closes":5,"positive_months_perc":"0.2778"},{"month":9,"ticker":"CVX","years":18,"sector":"Energy","max_change":"0.0912","min_change":"-0.1352","marketcap":"381251553837","avg_change":"0.0026","median_change":"0.0118","positive_closes":13,"positive_months_perc":"0.7222"},{"month":10,"ticker":"CVX","years":18,"sector":"Energy","max_change":"0.2143","min_change":"-0.1343","marketcap":"381251553837","avg_change":"0.0169","median_change":"0.0087","positive_closes":10,"positive_months_perc":"0.5556"},{"month":11,"ticker":"CVX","years":18,"sector":"Energy","max_change":"0.2331","min_change":"-0.0915","marketcap":"381251553837","avg_change":"0.0171","median_change":"0.0133","positive_closes":11,"positive_months_perc":"0.6111"},{"month":12,"ticker":"CVX","years":19,"sector":"Energy","max_change":"0.1108","min_change":"-0.1075","marketcap":"381251553837","avg_change":"0.0046","median_change":"0.0184","positive_closes":12,"positive_months_perc":"0.6316"}]